renpy_distribute_tools/__init__.py
renpy_distribute_tools/apple.py
renpy_distribute_tools/fixed_zipfile.py
renpy_distribute_tools/itch.py
renpy_distribute_tools/plist.py
renpy_distribute_tools/util.py
renpy_distribute_tools-0.4.1.post1.dist-info/LICENSE
renpy_distribute_tools-0.4.1.post1.dist-info/WHEEL
renpy_distribute_tools-0.4.1.post1.dist-info/METADATA
renpy_distribute_tools-0.4.1.post1.dist-info/RECORD
