Metadata-Version: 2.1
Name: renpy-distribute-tools
Version: 0.4.1.post1
Summary: Utilities that make Ren'Py distribution less of a pain in the arse
Home-page: https://github.com/UnscriptedVN/rdt
License: MIT
Author: Marquis Kurt
Author-email: software@marquiskurt.net
Requires-Python: >=3.7
Classifier: License :: OSI Approved :: MIT License
Classifier: Programming Language :: Python :: 3
Classifier: Programming Language :: Python :: 3.7
Classifier: Programming Language :: Python :: 3.8
Requires-Dist: pylint (>=2.4.4,<3.0.0)
Project-URL: Documentation, https://unscriptedvn.github.io/rdt/
